indextank
